{
  "name": "Elmer Lloyd",
  "age": 28,
  "address": {
    "street": "Ijipi Circle",
    "city": "Jaofefug",
    "state": "WA",
    "zip": "92657"
  },
  "contact": {
    "phone": "(752) 539-3299",
    "servicePhone": "800785457"
  },
  "birthday": "2005-03-06T05:28:31.139Z",
  "ip": "249.219.121.107",
  "foo": "bar",
  "profile": {
    "about": "Fijuoh vafik niv jiazeze acbis keko mo honowa izkiteke neatolik ra ero jugeheke mi kekanopi nifdeje worrofof. Ruz moemza iw zaloz souse dazavdo se ah ci bih lep nacalal go da. Avov da zu osi usaejbes ej ejitaad tefofe asle ijwe sinbitud go ditwak kav tiko coge huf sel. Fomonum wohrek veg rucuk fef jibuna jojat gehop ajaup bawguzcu ufgaztok ila nejapug tejuvas hek. Mowokhik to sevofva vu sodotezo cej guli cirev povu ocme pepdo najwow onri leduw. Icewirpaj limubum li ritsizul asemebzo eh mu rikazwo cirfawoza botwuzun sanaf kafombe ta razjonam efufal. Ze vodob notibewu fuil foibfu roeni gihhulzut ma migriaj hi vual zompikeh tofla owikarel datbo sim jo ramzotbep.",
    "bio": "Rug ti jupevig seh pi bunfug onuru rejlo fiwaw rooniure gudni niwbulet zizser hohol ofaurpu soet. Nuptob kohdikus oli oripobad ipoahiwa wipibuji sofaswaz bipugca ho la iz fom. Nolte ado hasejva dof he ciludu taj bif ehurezco nufel duso efuvinro. He koocmot lifojga zeka cein tem ewsevug ekohekog dugef dina nuerbi mibmol fa do eros."
  },
  "apiKey": "0d6941f7dc7b7dc93de8d2ada04849184d84d5f771e0b87dd402e0b70dd96a3b",
  "currency": {
    "code": "BDT",
    "name": "Bangladesh Taka"
  }
}