{
  "name": "Jerry Ballard",
  "age": 54,
  "address": {
    "street": "Diga Way",
    "city": "Vogudip",
    "state": "WI",
    "zip": "76065"
  },
  "contact": {
    "phone": "(731) 586-9113",
    "servicePhone": "800147384"
  },
  "birthday": "1961-08-24T20:49:33.235Z",
  "ip": "217.94.252.185",
  "foo": "bar",
  "profile": {
    "about": "Viv ifi nerudigol koheplem ilufam naibokod lojfun vafci fiphu paf di azihi aco igu utdo vebheru. Woihi ko igsec kiwgu dedsepbo joz ibobeede ba kifeju timnumuk wus riglo ih. Sostopli jorzawad izik fajo azijahace bafco vok koiwe oz wal oju hefa soec lemrubce jawrabwok hi.",
    "bio": "Leac zedra za behhoc sadapsiw ecosuen enjoso hus zeb ova jilkok cagawez mepenalat hep ru gacoj. Hu gip giiri bivofonu jigzagtop zuglic hozja nuh dabfemi jinhu bekucviw sof ip ufvil il. Vocat evebo ecajebpe rin hi fonrab pih puzu vol hasibwif zu sulkocfap domvoguz nibik wuzohjof utmarbo lisete. Nel pakew ro isi uzipo babvoza fusuaj oduri libjit otosub ruedkun peca sec gu. Ladcemda bogitbil mib ibu fof igarisi billol rartez ni ukes supez uvde dup kuwrut ga kihcudwat dug mivdaba. Va ziori vovude vigdemno celziger paf azmono inafoag diofeze bumgubmil je ni ga we ciate niwil. Pizcibvo moalo ob jeru jolju rutfaug wuzzi fumor nolewud jocuzojo rewnic puzkitep pen."
  },
  "apiKey": "2a4373b55ef4171ad7d315cbd40d5d7a40c0af9afb9f635f854714861ef90c9f",
  "currency": {
    "code": "MZN",
    "name": "Mozambique Metical"
  }
}